ha/__about__.py
ha/__init__.py
ha/beam.py
ha/ctc.py
ha/data.py
ha/loop.py
ha/model.py
ha/rnnlm.py
ha/star.py
ha/symbol_tape.py
ha/transducer.py
ha/xen.py
hecto_agent-0.0.3.dist-info/METADATA
hecto_agent-0.0.3.dist-info/WHEEL
hecto_agent-0.0.3.dist-info/entry_points.txt
hecto_agent-0.0.3.dist-info/RECORD
