Metadata-Version: 2.1
Name: hecto-agent
Version: 0.0.3
Summary: hecto speech agent for 100 hours
Project-URL: Documentation, https://github.com/proger/ha1#readme
Project-URL: Issues, https://github.com/proger/ha1/issues
Project-URL: Source, https://github.com/proger/ha1
Author-email: Volodymyr Kyrylov <vol@wilab.org.ua>
License-Expression: MIT
Classifier: Development Status :: 4 - Beta
Classifier: Programming Language :: Python
Classifier: Programming Language :: Python :: 3.9
Classifier: Programming Language :: Python :: 3.10
Classifier: Programming Language :: Python :: 3.11
Classifier: Programming Language :: Python :: Implementation :: CPython
Requires-Python: >=3.9
Requires-Dist: click
Requires-Dist: g2p-en
Requires-Dist: kaldialign
Requires-Dist: rich
Requires-Dist: torch
Requires-Dist: torchaudio
